markdownextradata/__init__.py
markdownextradata/plugin.py
mkdocs_markdownextradata_plugin-0.2.6.dist-info/LICENSE.md
mkdocs_markdownextradata_plugin-0.2.6.dist-info/METADATA
mkdocs_markdownextradata_plugin-0.2.6.dist-info/WHEEL
mkdocs_markdownextradata_plugin-0.2.6.dist-info/entry_points.txt
mkdocs_markdownextradata_plugin-0.2.6.dist-info/top_level.txt
mkdocs_markdownextradata_plugin-0.2.6.dist-info/RECORD
