Metadata-Version: 2.1
Name: mkdocs-markdownextradata-plugin
Version: 0.2.6
Summary: A MkDocs plugin that injects the mkdocs.yml extra variables into the markdown template
Home-page: https://github.com/rosscdh/mkdocs-markdownextradata-plugin/
Author: Ross Crawford-d'Heureuse
Author-email: sendrossemail@gmail.com
License: MIT
Keywords: mkdocs python markdown extra values
Classifier: Development Status :: 5 - Production/Stable
Classifier: Intended Audience :: Developers
Classifier: Intended Audience :: Information Technology
Classifier: License :: OSI Approved :: MIT License
Classifier: Programming Language :: Python
Classifier: Programming Language :: Python :: 3 :: Only
Classifier: Programming Language :: Python :: 3.6
Classifier: Programming Language :: Python :: 3.7
Classifier: Programming Language :: Python :: 3.8
Classifier: Programming Language :: Python :: 3.9
Classifier: Programming Language :: Python :: 3.10
Classifier: Programming Language :: Python :: 3.11
Requires-Python: >=3.6
License-File: LICENSE.md
Requires-Dist: mkdocs
Requires-Dist: pyyaml
